debug_agent/__init__.py
debug_agent/agent.py
debug_agent/agent_decorator.py
debug_agent/debugger_flow.py
debug_agent/logging_service.py
debug_agent/main.py
debug_agent/prompts/__init__.py
debug_agent/prompts/prompt_manager.py
debug_agent/prompts/templates/system_prompt.j2
debug_agent-0.1.1.dist-info/METADATA
debug_agent-0.1.1.dist-info/WHEEL
debug_agent-0.1.1.dist-info/licenses/LICENSE
debug_agent-0.1.1.dist-info/RECORD
