Metadata-Version: 2.4
Name: debug_agent
Version: 0.1.1
Summary: Add your description here
License-File: LICENSE
Requires-Python: >=3.12
Requires-Dist: jinja2>=3.1.6
Requires-Dist: langchain
Requires-Dist: langchain-huggingface>=0.3.0
Requires-Dist: langgraph>=0.4.10
Requires-Dist: pydantic>=2.11.7
Requires-Dist: requests>=2.32.4
Requires-Dist: smolagents>=1.19.0
